cigit/__init__.py
cigit/cigit.py
cigit/gitman.py
cigit/pipeline.py
cigit/utils.py
cigit-0.0.3.dist-info/entry_points.txt
cigit-0.0.3.dist-info/WHEEL
cigit-0.0.3.dist-info/METADATA
cigit-0.0.3.dist-info/licenses/LICENSE
cigit-0.0.3.dist-info/RECORD
