Metadata-Version: 2.1
Name: cigit
Version: 0.0.3
Summary: CI/CD Python Scripting
Author-email: hlop3z <23062270+hlop3z@users.noreply.github.com>
Requires-Python: >=3.10
Classifier: Intended Audience :: Developers
Classifier: License :: OSI Approved :: MIT License
Classifier: Programming Language :: Python :: 3
Classifier: Programming Language :: Python :: 3.10
Requires-Dist: pyyaml>=6.0
Project-URL: Documentation, https://hlop3z.github.io/cigit/
Project-URL: Homepage, https://github.com/hlop3z/cigit/
